{
  "version": "1.0",
  "task_id": "task-001",
  "implementation_contract": {
    "status": "approved",
    "planned_actions": [
      "intake SKILL.md: Replace 4 seed references with mission spec",
      "setup SKILL.md: Remove onboard reference from Phase A-1.5 title, remove entire Phase A-1.6 section",
      "specifying.md: Rename Seed Check→Spec Check, Onboard Check→Rules Check"
    ],
    "non_goals": [
      "No behavioral changes to any skill"
    ],
    "edge_cases": [
      "Preserve onboarding as general English in intake source field"
    ],
    "demo_steps": [
      "grep -w seed plugin/skills/ returns 0",
      "grep onboard plugin/skills/setup/SKILL.md returns 0"
    ]
  },
  "created_at": "2026-04-10T13:04:50Z",
  "self_check": {
    "confidence": 5,
    "known_risks": [],
    "untested_paths": [],
    "summary": "All 3 files edited. grep confirms zero deprecated terms. Setup inputs section dangling reference also fixed."
  },
  "updated_at": "2026-04-10T13:10:13Z",
  "gate_result": {
    "verdict": "pass",
    "tier_results": {
      "tier_0": {
        "status": "pass",
        "details": "All evidence artifacts exist"
      },
      "tier_1": {
        "status": "skipped",
        "details": "No eval commands for artifact_only gate"
      },
      "tier_2": {
        "status": "pass",
        "details": "All 5 acceptance criteria met"
      }
    },
    "rubric_scores": [
      {
        "dimension": "core_interaction",
        "score": 5,
        "threshold": 3,
        "passed": true
      },
      {
        "dimension": "feature_completeness",
        "score": 5,
        "threshold": 4,
        "passed": true
      },
      {
        "dimension": "code_quality",
        "score": 5,
        "threshold": 4,
        "passed": true
      },
      {
        "dimension": "regression_safety",
        "score": 5,
        "threshold": 4,
        "passed": true
      }
    ],
    "blocking_dimensions": []
  },
  "closure": {
    "change_summary": "Removed deprecated terms from 3 skill files: seed→mission spec in intake SKILL.md, onboard reference and Phase A-1.6 migration section from setup SKILL.md, header renames in specifying.md. Also removed dangling input reference.",
    "reviews": [
      {
        "reviewer_type": "design-authority",
        "status": "approved",
        "summary": "All changes strictly terminological, no behavioral impact"
      }
    ],
    "open_risks": [],
    "debt_items": [
      "setup SKILL.md Output section still lists .gitignore update which may be outdated"
    ]
  },
  "verdict": {
    "verdict": "pass",
    "rationale": "Low-risk terminology cleanup. All deprecated terms (seed, onboard, Phase A-1.6) removed from 3 skill files. Design-authority approved with no concerns. Grep verification confirms zero residual hits. Debt item (setup .gitignore output) is out of scope and minor."
  },
  "retrospective": {
    "what_went_well": [
      "Clean focused edits",
      "Agent caught dangling input reference"
    ],
    "what_broke": [],
    "what_was_surprising": [
      "specifying.md missed in original scope — design-authority caught it"
    ],
    "rule_candidates": [],
    "memory_candidates": [
      "Check references/ subdirs when scoping terminology cleanup"
    ],
    "debt_candidates": [
      "vote-round and reporting SKILLS.md descriptions still have Absorbed the former... pattern"
    ],
    "next_time_guidance": [
      "Check references/ subdirectories when scoping terminology cleanup"
    ]
  }
}
